docs/index.md
gitblog2/__init__.py
gitblog2/blog_posts.py
gitblog2/cli.py
gitblog2/lib.py
gitblog2/media/favicon.svg
gitblog2/media/icons.svg
gitblog2/repo_utils.py
gitblog2/style.css
gitblog2/templates/article.html.j2
gitblog2/templates/footer.html.j2
gitblog2/templates/head_common.html.j2
gitblog2/templates/index.html.j2
gitblog2/templates/navbar.html.j2
gitblog2/tests/example_output/index.html
gitblog2/tests/example_output/media/favicon.svg
gitblog2/tests/example_output/media/icons.svg
gitblog2/tests/example_output/style.css
gitblog2/tests/example_output/tech/example.html
gitblog2/tests/example_output/tech/index.html
gitblog2/tests/test_e2e.py
gitblog2/utils.py
gitblog2-2.3.0.dist-info/METADATA
gitblog2-2.3.0.dist-info/entry_points.txt
gitblog2-2.3.0.dist-info/LICENSE
gitblog2-2.3.0.dist-info/WHEEL
gitblog2-2.3.0.dist-info/RECORD
