Metadata-Version: 2.1
Name: gitblog2
Version: 2.3.0
Summary: Git + Markdown = blog
Home-page: https://github.com/HenriTEL/gitblog2
License: MIT
Author: Henri Hannetel
Author-email: henri.hannetel@pm.me
Requires-Python: >=3.8
Classifier: License :: OSI Approved :: MIT License
Classifier: Programming Language :: Python :: 3
Classifier: Programming Language :: Python :: 3.8
Classifier: Programming Language :: Python :: 3.9
Classifier: Programming Language :: Python :: 3.10
Classifier: Programming Language :: Python :: 3.11
Requires-Dist: Jinja2 (>=3.1.2,<4.0.0)
Requires-Dist: Markdown (>=3.4.1,<4.0.0)
Requires-Dist: feedgen (>=0.9.0,<0.10.0)
Requires-Dist: gitpython (>=3.1.36,<4.0.0)
Requires-Dist: requests (>=2.28.2,<3.0.0)
Requires-Dist: typer (>=0.7.0)
Project-URL: Documentation, https://henritel.github.io/gitblog2
Project-URL: Repository, https://github.com/HenriTEL/gitblog2
